{
  "attributes": [
    {
      "default": "nil",
      "size": null,
      "type": "uuid",
      "source": "id",
      "references": null,
      "allow_nil?": false,
      "generated?": false,
      "primary_key?": true
    },
    {
      "default": "nil",
      "size": null,
      "type": "bigint",
      "source": "season_number",
      "references": null,
      "allow_nil?": false,
      "generated?": false,
      "primary_key?": false
    },
    {
      "default": "nil",
      "size": null,
      "type": "bigint",
      "source": "episode_number",
      "references": null,
      "allow_nil?": false,
      "generated?": false,
      "primary_key?": false
    },
    {
      "default": "nil",
      "size": null,
      "type": "float",
      "source": "position_seconds",
      "references": null,
      "allow_nil?": true,
      "generated?": false,
      "primary_key?": false
    },
    {
      "default": "nil",
      "size": null,
      "type": "float",
      "source": "duration_seconds",
      "references": null,
      "allow_nil?": true,
      "generated?": false,
      "primary_key?": false
    },
    {
      "default": "nil",
      "size": null,
      "type": "boolean",
      "source": "completed",
      "references": null,
      "allow_nil?": true,
      "generated?": false,
      "primary_key?": false
    },
    {
      "default": "nil",
      "size": null,
      "type": "utc_datetime",
      "source": "last_watched_at",
      "references": null,
      "allow_nil?": true,
      "generated?": false,
      "primary_key?": false
    },
    {
      "default": "nil",
      "size": null,
      "type": "utc_datetime_usec",
      "source": "inserted_at",
      "references": null,
      "allow_nil?": false,
      "generated?": false,
      "primary_key?": false
    },
    {
      "default": "nil",
      "size": null,
      "type": "utc_datetime_usec",
      "source": "updated_at",
      "references": null,
      "allow_nil?": false,
      "generated?": false,
      "primary_key?": false
    },
    {
      "default": "nil",
      "size": null,
      "type": "uuid",
      "source": "entity_id",
      "references": {
        "name": "watch_progress_entity_id_fkey",
        "table": "entities",
        "multitenancy": {
          "global": null,
          "attribute": null,
          "strategy": null
        },
        "on_delete": null,
        "primary_key?": true,
        "destination_attribute": "id",
        "deferrable": false,
        "destination_attribute_default": null,
        "destination_attribute_generated": null,
        "on_update": null
      },
      "allow_nil?": true,
      "generated?": false,
      "primary_key?": false
    }
  ],
  "table": "watch_progress",
  "hash": "871DCB6C8EF0B4ABB3E1599A2050AB06B011D72401298915EEAFF38D0BFF7109",
  "multitenancy": {
    "global": null,
    "attribute": null,
    "strategy": null
  },
  "identities": [
    {
      "name": "unique_playable_item",
      "keys": [
        "entity_id",
        "season_number",
        "episode_number"
      ],
      "index_name": "watch_progress_unique_playable_item_index",
      "base_filter": null
    }
  ],
  "repo": "Elixir.MediaManager.Repo",
  "strict?": false,
  "custom_indexes": [],
  "base_filter": null,
  "custom_statements": [],
  "has_create_action": true
}